git2effort-0.1.4-py3.6-nspkg.pth
git2effort/_version.py
git2effort/effort.py
git2effort/merging.py
git2effort-0.1.4.data/scripts/git2effort
git2effort-0.1.4.dist-info/AUTHORS
git2effort-0.1.4.dist-info/LICENSE
git2effort-0.1.4.dist-info/METADATA
git2effort-0.1.4.dist-info/WHEEL
git2effort-0.1.4.dist-info/namespace_packages.txt
git2effort-0.1.4.dist-info/top_level.txt
git2effort-0.1.4.dist-info/RECORD
