Metadata-Version: 2.1
Name: git2effort
Version: 0.1.4
Summary: Calculate development effort from a Git repository
Home-page: https://github.com/gregoriorobles/git2effort
Author: Gregorio Robles
Author-email: grex@gsyc.urjc.es
License: GPLv3
Keywords: effort development repositories analytics git github
Platform: UNKNOWN
Classifier: Development Status :: 2 - Pre-Alpha
Classifier: Environment :: Console
Classifier: Intended Audience :: Developers
Classifier: Intended Audience :: Science/Research
Classifier: Topic :: Software Development
Classifier: License :: OSI Approved :: GNU General Public License v3 or later (GPLv3+)
Classifier: Programming Language :: Python :: 3
Requires-Dist: perceval (>=0.12)
Requires-Dist: python-dateutil (>=2.6.0)
Requires-Dist: requests (>=2.7.0)
Requires-Dist: beautifulsoup4 (>=4.3.2)
Requires-Dist: feedparser (>=5.1.3)
Requires-Dist: dulwich (<0.19,>=0.18.5)
Requires-Dist: urllib3 (>=1.22)
Requires-Dist: tabulate (>=0.8.7)
